mysocketctl/__init__.py
mysocketctl/account.py
mysocketctl/connect.py
mysocketctl/login.py
mysocketctl/mysocketcli.py
mysocketctl/socket.py
mysocketctl/tunnel.py
mysocketctl/utils.py
mysocketctl/ssh/__init__.py
mysocketctl/ssh/paramiko_client.py
mysocketctl/ssh/system.py
mysocketctl-0.15.dist-info/LICENSE
mysocketctl-0.15.dist-info/METADATA
mysocketctl-0.15.dist-info/WHEEL
mysocketctl-0.15.dist-info/entry_points.txt
mysocketctl-0.15.dist-info/top_level.txt
mysocketctl-0.15.dist-info/RECORD
