Metadata-Version: 2.1
Name: mysocketctl
Version: 0.15
Summary: CLI tool for mysocket.io
Home-page: https://github.com/mysocketio/mysocketctl
Author: Andree Toonk
Author-email: andree@mysocket.io
License: Apache Software License
Platform: UNKNOWN
Classifier: Intended Audience :: Developers
Classifier: License :: OSI Approved :: Apache Software License
Classifier: Operating System :: MacOS :: MacOS X
Classifier: Operating System :: POSIX
Classifier: Programming Language :: Python
Classifier: Programming Language :: Python :: 3
Classifier: Programming Language :: Python :: 3 :: Only
Classifier: Programming Language :: Python :: 3.5
Classifier: Programming Language :: Python :: 3.6
Classifier: Programming Language :: Python :: 3.7
Classifier: Programming Language :: Python :: 3.8
Classifier: Programming Language :: Python :: 3.9
Classifier: Programming Language :: Python :: Implementation :: CPython
Classifier: Programming Language :: Python :: Implementation :: PyPy
Classifier: Topic :: Software Development :: Libraries :: Python Modules
Requires-Python: >=3.6
Requires-Dist: Click
Requires-Dist: requests
Requires-Dist: pyjwt (==1.7.1)
Requires-Dist: prettytable
Requires-Dist: paramiko
Requires-Dist: validate-email
